README.md
setup.py
src/masonite/api/__init__.py
src/masonite/api/exceptions.py
src/masonite/api/authentication/BaseAuthentication.py
src/masonite/api/authentication/JWTAuthentication.py
src/masonite/api/authentication/PermissionScopes.py
src/masonite/api/authentication/TokenAuthentication.py
src/masonite/api/authentication/__init__.py
src/masonite/api/controllers/TokenController.py
src/masonite/api/controllers/__init__.py
src/masonite/api/filters/FilterScopes.py
src/masonite/api/filters/__init__.py
src/masonite/api/guards/APIGuard.py
src/masonite/api/guards/APIJwtDriver.py
src/masonite/api/guards/__init__.py
src/masonite/api/providers/ApiProvider.py
src/masonite/api/providers/__init__.py
src/masonite/api/resources/Resource.py
src/masonite/api/resources/__init__.py
src/masonite/api/routes/TokenRoutes.py
src/masonite/api/routes/__init__.py
src/masonite/api/serializers/JSONSerializer.py
src/masonite/api/serializers/XMLSerializer.py
src/masonite/api/serializers/__init__.py
src/masonite_api.egg-info/PKG-INFO
src/masonite_api.egg-info/SOURCES.txt
src/masonite_api.egg-info/dependency_links.txt
src/masonite_api.egg-info/requires.txt
src/masonite_api.egg-info/top_level.txt